[
    {
      "title": "Shape of You",
      "times_played": 2000000,
      "period_of_time": "2023-01-01 to 2023-07-18"
    },
    {
      "title": "Someone Like You",
      "times_played": 1800000,
      "period_of_time": "2023-01-01 to 2023-07-18"
    },
    {
      "title": "Billie Jean",
      "times_played": 1600000,
      "period_of_time": "2023-01-01 to 2023-07-18"
    },
    {
      "title": "Bohemian Rhapsody",
      "times_played": 1400000,
      "period_of_time": "2023-01-01 to 2023-07-18"
    },
    {
      "title": "Imagine",
      "times_played": 1300000,
      "period_of_time": "2023-01-01 to 2023-07-18"
    },
    {
      "title": "Hotel California",
      "times_played": 1200000,
      "period_of_time": "2023-01-01 to 2023-07-18"
    },
    {
      "title": "Like a Rolling Stone",
      "times_played": 1100000,
      "period_of_time": "2023-01-01 to 2023-07-18"
    },
    {
      "title": "Rolling in the Deep",
      "times_played": 1000000,
      "period_of_time": "2023-01-01 to 2023-07-18"
    },
    {
      "title": "Thriller",
      "times_played": 950000,
      "period_of_time": "2023-01-01 to 2023-07-18"
    },
    {
      "title": "Boogie Wonderland",
      "times_played": 900000,
      "period_of_time": "2023-01-01 to 2023-07-18"
    }
  ]